{"_ts":[1561950132,1561977317,1561984627,1561988451,1561990079,1562006811,1562039169,1562077645,1562079003,1562121716,1562165117,1562209223,1562254131,1562297218,1562332019,1562341388,1562385638,1562429170,1562473324,1562517375,1562561321,1562605271,1562649358],"_r":{"breakdown":{"html":{"bytes":[0,0,0,0,0,0,0,0,0,0,0,0,0,0,0,0,0,0,0,0,0,0,0],"requests":[0,0,0,0,0,0,0,0,0,0,0,0,0,0,0,0,0,0,0,0,0,0,0]},"js":{"bytes":[0,0,0,0,0,0,0,0,0,0,0,0,0,0,0,0,0,0,0,0,0,0,0],"requests":[0,0,0,0,0,0,0,0,0,0,0,0,0,0,0,0,0,0,0,0,0,0,0]},"css":{"bytes":[0,0,0,0,0,0,0,0,0,0,0,0,0,0,0,0,0,0,0,0,0,0,0],"requests":[0,0,0,0,0,0,0,0,0,0,0,0,0,0,0,0,0,0,0,0,0,0,0]},"image":{"bytes":[0,0,0,0,0,0,0,0,0,0,0,0,0,0,0,0,0,0,0,0,0,0,0],"requests":[0,0,0,0,0,0,0,0,0,0,0,0,0,0,0,0,0,0,0,0,0,0,0]},"flash":{"bytes":[0,0,0,0,0,0,0,0,0,0,0,0,0,0,0,0,0,0,0,0,0,0,0],"requests":[0,0,0,0,0,0,0,0,0,0,0,0,0,0,0,0,0,0,0,0,0,0,0]},"font":{"bytes":[0,0,0,0,0,0,0,0,0,0,0,0,0,0,0,0,0,0,0,0,0,0,0],"requests":[0,0,0,0,0,0,0,0,0,0,0,0,0,0,0,0,0,0,0,0,0,0,0]},"video":{"bytes":[0,0,0,0,0,0,0,0,0,0,0,0,0,0,0,0,0,0,0,0,0,0,0],"requests":[0,0,0,0,0,0,0,0,0,0,0,0,0,0,0,0,0,0,0,0,0,0,0]},"other":{"bytes":[0,0,0,0,0,0,0,0,0,0,0,0,0,0,0,0,0,0,0,0,0,0,0],"requests":[0,0,0,0,0,0,0,0,0,0,0,1,0,0,0,0,0,0,0,0,1,0,0]}},"date":[1561950132,1561977317,1561984627,1561988451,1561990079,1562006811,1562039169,1562077645,1562079003,1562121716,1562165117,1562209223,1562254131,1562297218,1562332019,1562341388,1562385638,1562429170,1562473324,1562517375,1562561321,1562605271,1562649358],"domElements":[null,null,null,null,null,null,null,null,null,null,null,null,null,null,null,null,null,null,null,null,null,null,null],"domInteractive":[null,null,null,null,null,null,null,null,null,null,null,null,null,null,null,null,null,null,null,null,null,null,null],"firstPaint":[null,null,null,null,null,null,null,null,null,null,null,null,null,null,null,null,null,null,null,null,null,null,null],"fullyLoaded":[null,null,null,null,null,null,null,null,null,null,null,null,null,null,null,null,null,null,null,null,null,null,null],"id":["190701_RP_9f5e93f79de6214f68ecd09a5e72edef","190701_FS_298f186c04c06ae4500319049eac81de","190701_KN_7fd31a5b0e4c99ae4980e1c2ab58da62","190701_0K_886bbbbd5932395546b9b03095d1453e","190701_0B_75fd85768e537bdd9430879928128b48","190701_N0_35bb6b421edfd5b4067eb01b6611f459","190702_WS_55494ad07494b4e7a13c1eb048b04bad","190702_2E_735e5dd4100fadcf1e3169573bb521e2","190702_94_f6293fa9d30971127025aae5fc86234c","190703_JG_4e10ce3a269fea3a3bdbb1b52c6f717e","190703_0M_661d242193c8294cd4eddafe4098cca5","190704_W4_9c3f753d32b0de44d36b70b7f631d3f5","190704_JS_9f5880843c5f996efe827d2ab1c19d2f","190705_W7_f49b9d84b7f21d3691b210c2af989fbf","190705_95_43ae626ae9dbd537bad620540665945c","190705_6S_441c6dfdb55f03f161c952a12bc1115f","190706_WC_d2bf93f90bf59cd701513b2d3ee694f5","190706_NH_860bb1d65f7ebbf5c7e34209ce4590f1","190707_RQ_532c9715e9f8400312a9bb8776a7d9f2","190707_ES_02e09dde840599f22b86a2e806a44e9b","190708_CB_2335b8e7691465aa27bb329290c8c9bf","190708_GW_1fe79839f03b0845ac4083ae6b87c64c","190709_2Z_6ced720d2841183f25b7b4e0a118a739"],"loadTime":[null,null,null,null,null,null,null,null,null,null,null,null,null,null,null,null,null,null,null,null,null,null,null],"render":[null,null,null,null,null,null,null,null,null,null,null,null,null,null,null,null,null,null,null,null,null,null,null],"SpeedIndex":[null,null,null,null,null,null,null,null,null,null,null,null,null,null,null,null,null,null,null,null,null,null,null],"TTFB":[null,null,null,null,null,null,null,null,null,null,null,null,null,null,null,null,null,null,null,null,null,null,null],"videoFrames":[[{"_i":"ms_000000.jpg","_t":0,"_vc":100}],[{"_i":"ms_000000.jpg","_t":0,"_vc":100}],[{"_i":"ms_000000.jpg","_t":0,"_vc":100}],[{"_i":"ms_000000.jpg","_t":0,"_vc":100}],[{"_i":"ms_000000.jpg","_t":0,"_vc":100}],[{"_i":"ms_000000.jpg","_t":0,"_vc":100}],[{"_i":"ms_000000.jpg","_t":0,"_vc":100}],[{"_i":"ms_000000.jpg","_t":0,"_vc":100}],[{"_i":"ms_000000.jpg","_t":0,"_vc":100}],[{"_i":"ms_000000.jpg","_t":0,"_vc":100}],[{"_i":"ms_000000.jpg","_t":0,"_vc":100}],[{"_i":"ms_000000.jpg","_t":0,"_vc":100}],[{"_i":"ms_000000.jpg","_t":0,"_vc":100}],[{"_i":"ms_000000.jpg","_t":0,"_vc":100}],[{"_i":"ms_000000.jpg","_t":0,"_vc":100}],[{"_i":"ms_000000.jpg","_t":0,"_vc":100}],[{"_i":"ms_000000.jpg","_t":0,"_vc":100}],[{"_i":"ms_000000.jpg","_t":0,"_vc":100}],[{"_i":"ms_000000.jpg","_t":0,"_vc":100}],[{"_i":"ms_000000.jpg","_t":0,"_vc":100}],[{"_i":"ms_000000.jpg","_t":0,"_vc":100}],[{"_i":"ms_000000.jpg","_t":0,"_vc":100}],[{"_i":"ms_000000.jpg","_t":0,"_vc":100}]],"visualComplete":[null,null,null,null,null,null,null,null,null,null,null,null,null,null,null,null,null,null,null,null,null,null,null],"lighthouse":[null,null,null,null,null,null,null,null,null,null,null,null,null,null,null,null,null,null,null,null,null,null,null],"pagespeed":[null,null,null,null,null,null,null,null,null,null,null,null,null,null,null,null,null,null,null,null,null,null,null]}}